mopidy_autoplay/__init__.py
mopidy_autoplay/ext.conf
mopidy_autoplay/frontend.py
Mopidy_Autoplay-0.2.3.dist-info/LICENSE
Mopidy_Autoplay-0.2.3.dist-info/METADATA
Mopidy_Autoplay-0.2.3.dist-info/WHEEL
Mopidy_Autoplay-0.2.3.dist-info/entry_points.txt
Mopidy_Autoplay-0.2.3.dist-info/top_level.txt
Mopidy_Autoplay-0.2.3.dist-info/RECORD
